{
    "0.6722": {
        "x_bounds": "min x: -2.9999 max x: 2.9999",
        "orig_len": "length of dataset: 100000",
        "y_bounds": "min y: -3.0 max y: 3.0",
        "setno": "22",
        "expno": "0.6722",
        "Precision_used": "64",
        "cuda": "CUDA is available. Proceeding with the program.",
        "arguments": [
            "src/run_smlp.py",
            "-data",
            "smlp_toy_basic",
            "-out_dir",
            "toy_out_dir",
            "-pref",
            "abc",
            "-mode",
            "optimize",
            "-pareto",
            "t",
            "-resp",
            "y",
            "-feat",
            "x",
            "-model",
            "nn_keras",
            "-data_scaler",
            "min_max",
            "-epsilon",
            "0.05",
            "-delta_abs",
            "0.01",
            "-save_model_config",
            "f",
            "-mrmr_pred",
            "0",
            "-plots",
            "f",
            "-seed",
            "10",
            "-log_time",
            "f",
            "-spec",
            "smlp_toy_basic.spec"
        ]
    }
}